godale/__init__.py
godale/_concurrent.py
scripts/__init__.py
scripts/run_tests.py
scripts/worker_func.py
godale-0.3.dist-info/LICENSE
godale-0.3.dist-info/METADATA
godale-0.3.dist-info/WHEEL
godale-0.3.dist-info/top_level.txt
godale-0.3.dist-info/RECORD
