Metadata-Version: 2.1
Name: godale
Version: 0.3
Summary: concurrent execution in various flavors
Home-page: UNKNOWN
Author: Joachim Ungar
Author-email: joachim.ungar@eox.at
License: MIT
Platform: UNKNOWN
Classifier: Development Status :: 3 - Alpha
Classifier: Intended Audience :: Developers
Classifier: Topic :: Scientific/Engineering
Classifier: License :: OSI Approved :: MIT License
Classifier: Programming Language :: Python :: 3.6
Classifier: Programming Language :: Python :: 3.7
Requires-Dist: billiard
